Metadata-Version: 2.1
Name: odoo11-addon-l10n-es-facturae
Version: 11.0.1.1.1
Summary: Creación de Factura-e
Home-page: https://github.com/OCA/l10n-spain
Author: ASR-OSS, FactorLibre, Tecon, Comunitea, Tecnativa, Creu Blanca, Odoo Community Association (OCA)
Author-email: support@odoo-community.org
License: AGPL-3
Platform: UNKNOWN
Classifier: Programming Language :: Python
Classifier: Framework :: Odoo
Classifier: License :: OSI Approved :: GNU Affero General Public License v3
Requires-Python: >=2.7, !=3.0.*, !=3.1.*, !=3.2.*, !=3.3.*, !=3.4.*
Requires-Dist: odoo11-addon-account-banking-mandate
Requires-Dist: odoo11-addon-account-payment-partner
Requires-Dist: odoo11-addon-base-iso3166
Requires-Dist: odoo11-addon-l10n-es-partner
Requires-Dist: odoo11-addon-partner-firstname
Requires-Dist: odoo11-addon-report-qweb-parameter
Requires-Dist: odoo11-addon-report-xml
Requires-Dist: odoo (<11.1dev,>=11.0a)
Requires-Dist: pyOpenSSL
Requires-Dist: xmlsig
